[
  {
    "platform": "epic",
    "title": "Fear the Spotlight",
    "subtitle": "Epic Games Store",
    "source_url": "https://store.epicgames.com/en-US/free-games",
    "store_product_url": "https://store.epicgames.com/en-US/p/fear-the-spotlight-97656f",
    "image_url": "https://cdn1.epicgames.com/spt-assets/7440e6952704438cbb2e4f4dff02e00a/fear-the-spotlight-1ioq7.jpg",
    "price_before": "$19.99",
    "price_now": "0",
    "currency": "USD",
    "region_scope": "Global",
    "starts_at": "2025-10-23T15:00:00.000Z",
    "ends_at": "2025-10-30T15:00:00.000Z",
    "is_time_limited": true,
    "tags": [
      "freegames",
      "games",
      "games/edition",
      "games/edition/base"
    ],
    "rating": null,
    "verified_at": "2025-10-26T09:16:37.868Z"
  }
]